{
    "id": 227,
    "lang": "pt",
    "is_original": true,
    "title": "Antas (Conde das)",
    "fl": "A",
    "original_title": "Antas (Conde das)",
    "body": "O major Francisco Xavier Pereira da Silva, mais tarde conde das Antas e que tanto se distinguiu nas campanhas da liberdade, esteve na Madeira em 1828 a fim de auxiliar o governador e capitão general Travassos Valdez na defesa que este preparava contra o ataque da esquadra miguelista, Pereira da Silva tinha chegado ao Funchal, vindo de Inglaterra, no dia 20 de Agosto de 1828 e fora logo encarregado da defesa de alguns pontos estratégicos nas alturas do Caniço, mas as forças liberais viram-se forçadas a ceder perante as tropas invasoras, e aquele oficial, juntamente com Valdez e outros indivíduos, embarcaram a bordo da corveta inglesa Alligator e seguiram para Inglaterra.\n\n## V. Alligator (Corveta) e Ocupação da Madeira pelas tropas miguelistas.",
    "categories": [
        "history"
    ],
    "freguesias": [],
    "locations": {},
    "people": {
        "Francisco Xavier Pereira da Silva": [
            "Major e posteriormente conde das Antas"
        ]
    },
    "years": {
        "1828": [
            "Presença do major Francisco Xavier Pereira da Silva na Madeira"
        ]
    }
}