{
    "id": 2542,
    "lang": "pt",
    "is_original": true,
    "title": "Novidades (As)",
    "fl": "N",
    "original_title": "Novidades (As)",
    "body": "Com este título publicou-se no Funchal um periódico, que deu o primeiro numero a\n\n 26 de Julho de 1866.\n\n\n Outro Jornal que aqui se publicou com o mesmo título, apareceu a 18 de Novembro de 1881 e deu vinte e\n\n seis números, o ultimo dos quais a 24 de Dezembro de 1882.",
    "categories": [
        "history"
    ],
    "freguesias": [],
    "locations": {},
    "people": {},
    "years": {
        "1866": [
            "Publicação do periódico 'Novidades'"
        ],
        "1881": [
            "Publicação do outro jornal 'Novidades'"
        ],
        "1882": [
            "Último número do jornal 'Novidades'"
        ]
    }
}