{
    "id": 2717,
    "lang": "pt",
    "is_original": true,
    "title": "Pena (A)",
    "fl": "P",
    "original_title": "Pena (A)",
    "body": "Numero unico dum jornal que, em homenagem ao conselheiro dr. José Leite Monteiro, se publicou em Maio de 1908.",
    "categories": [],
    "freguesias": [],
    "locations": {},
    "people": {
        "José Leite Monteiro": [
            "Conselheiro homenageado com a publicação de um número único de um jornal em Maio de 1908."
        ]
    },
    "years": {
        "1908": [
            "Mês em que foi publicado um número único de um jornal em homenagem ao conselheiro dr. José Leite Monteiro."
        ]
    }
}