{
    "id": 49,
    "lang": "pt",
    "is_original": true,
    "title": "Adams (J.)",
    "fl": "A",
    "original_title": "Adams (J.)",
    "body": "Médico inglês que obteve, em 1802, licença do Governador e Capitão General para vacinar todas as semanas 4 a 6 expostos, que para esse fim deviam ir a sua casa. Foi, segundo parece, o primeiro médico que aplicou a vacina na Madeira. E.: A Guide to Madeira with an account of the Climate (Londres 1901).",
    "categories": [
        "health"
    ],
    "freguesias": [],
    "locations": {},
    "people": {
        "J. Adams": [
            "Médico inglês"
        ]
    },
    "years": {
        "1802": [
            "Licença para vacinar"
        ]
    }
}