{
    "id": 1562,
    "lang": "de",
    "is_original": false,
    "title": "Zackenbarsch (Serranus cabrilla)",
    "fl": "Z",
    "original_title": "Garoupa (Serranus cabrilla)",
    "body": "Fisch der Familie Percida, der die felsigen Flachwassergebiete von der Küste bis etwas über 100 Klafter bewohnt. Die Briqueira ist der in der Regel zum Fang verwendete Apparat.\n\nNeben seiner Häufigkeit ist der Zackenbarsch einer der feinsten Fische in den Meeren Madeiras.",
    "categories": [
        "biology"
    ],
    "freguesias": [],
    "locations": {},
    "people": {},
    "years": {}
}