{
    "id": 1869,
    "lang": "de",
    "is_original": false,
    "title": "Juiz do Povo",
    "fl": "J",
    "original_title": "Juiz do Povo",
    "body": "Er wurde vom Haus der Vierundzwanzig (siehe diesen Namen) gewählt, vertrat die Volksklassen gegenüber verschiedenen Körperschaften und Behörden und hatte bestimmte administrative Befugnisse. Er spielte inoffiziell die Rolle eines Vermittlers zwischen dem Volk und den örtlichen Behörden, insbesondere in Fällen, in denen die Rechtsvorschriften nicht eindeutig klar waren, und konnte nicht ohne mindestens sechs Jahre Mitgliedschaft im Haus der Vierundzwanzig gewählt werden.\n\nGemäß einem Beschluss des Senats der Stadt Funchal vom 22. Dezember 1802 saß der Volksrichter, wenn er \"wegen einer Angelegenheit erschien\", auf einem flachen Stuhl (Stühle mit Lehnen waren für Ratsmitglieder und den Schreiber bestimmt) über dem ältesten der Handwerksmeister.\n\nWir wissen nicht, wann bei uns das Amt des Volksrichters geschaffen wurde, das bis 1834 bestand.",
    "categories": [
        "history",
        "society"
    ],
    "freguesias": [],
    "locations": {
        "Funchal": [
            "Stadt Funchal"
        ]
    },
    "people": {
        "Senats der Stadt Funchal": [
            "Regierungsorgan"
        ]
    },
    "years": {
        "1802": [
            "Beschluss des Senats der Stadt Funchal"
        ]
    }
}