{
    "id": 2479,
    "lang": "de",
    "is_original": false,
    "title": "Unsere Liebe Frau vom Stuhl (Kapelle)",
    "fl": "U",
    "original_title": "Nossa Senhora da Cadeira (Capela de)",
    "body": "Mit diesem Namen gab es eine Kapelle im Ort Cadeirinha, die innerhalb der heutigen Grenzen der Gemeinde Quinta Grande lag und die eine andere, in Vergessenheit geratene Anrufung gehabt haben soll.\n\nIn derselben Pfarrei gab es auch eine der Jungfrau Maria geweihte Einsiedelei, die den Namen Kapelle des Tors von Quinta trug.",
    "categories": [
        "religion"
    ],
    "freguesias": [
        "Quinta Grande"
    ],
    "locations": {},
    "people": {},
    "years": {}
}