{
    "id": 2871,
    "lang": "de",
    "is_original": false,
    "title": "Porto Santo (Orografie)",
    "fl": "P",
    "original_title": "Porto Santo (Orografia)",
    "body": "Diese relativ kleine Insel hat ein gebirgiges Aussehen und ist von sehr unebenem Gelände geprägt, wobei der Pico do Castelo, über den wir bereits auf Seite 259 des ersten Bandes dieses Werks berichtet haben, sich 440 Meter über den Meeresspiegel erhebt.\n\nDie wichtigsten Erhebungen in der Gebirgskette der Insel sind die folgenden, die allgemein als Gipfel bezeichnet werden: Ninho do Guincho, Branco (423m), Concelho, Maçaricos, de Baixo, Juliana (455m), Facho (509m), Atalaia oder Gandaia (492m), Castelo, Monte Vidio, Ana Ferreira, Facho da Malhada (265m) und Calhau da Malhada (182m).\n\nTrotz des ausgeprägten Reliefs gibt es zwei kleine Ebenen, die erwähnt werden sollten: die von Vila und die von Areias.\n\nDie wichtigsten Kaps und Vorsprünge der Meeresküste sind: Cruz oder Santa Cruz, Ninho do Guincho, Branca oder Nordeste, Frades, Incão, Calheta, Malhada, Furado, Varadouros und Fonte da Areia.",
    "categories": [
        "geography"
    ],
    "freguesias": [],
    "locations": {},
    "people": {},
    "years": {}
}