{
    "id": 2379,
    "lang": "en",
    "is_original": false,
    "title": "Morgado Esmeraldo (Estrada do)",
    "fl": "M",
    "original_title": "Morgado Esmeraldo (Estrada do)",
    "body": "Connects the church of S. Martinho with the site of Pilar. The estate at the northern end of the road that bears its name belonged to the Morgado Esmeraldo.",
    "categories": [
        "geography"
    ],
    "freguesias": [
        "S. Martinho"
    ],
    "locations": {},
    "people": {},
    "years": {}
}