{
    "id": 3369,
    "lang": "en",
    "is_original": false,
    "title": "Sociedade Auxiliadora da Instrução Primaria",
    "fl": "S",
    "original_title": "Sociedade Auxiliadora da Instrução Primaria",
    "body": "> On October 19, 1858, a select assembly met at the São Lourenço Palace to lay the foundations of an association aimed at promoting and supporting primary education in this district, with several speakers addressing the assembly. The Infante D. Luis, later king of Portugal, attended this meeting and declared himself the protector of the new association.",
    "categories": [
        "education",
        "society"
    ],
    "freguesias": [],
    "locations": {
        "Palácio de São Lourenço": [
            "Location of the meeting of the Sociedade Auxiliadora da Instrução Primaria"
        ]
    },
    "people": {
        "D. Luis": [
            "Infante D. Luis, later king of Portugal"
        ]
    },
    "years": {
        "1858": [
            "Meeting of the Sociedade Auxiliadora da Instrução Primaria"
        ]
    }
}