{
    "id": 947,
    "lang": "en",
    "is_original": false,
    "title": "Colvocoress (Lieut. Gio. M.)",
    "fl": "C",
    "original_title": "Colvocoress (Lieut. Gio. M.)",
    "body": "E.: Four years in the government exploring expedition commanded by captain Charles Wilkes to the Island of Madeira, Cape Verdes, Brazil...; New-York, 1858 (20th edition).",
    "categories": [
        "history"
    ],
    "freguesias": [],
    "locations": {},
    "people": {
        "Charles Wilkes": [
            "Captain of the expedition"
        ]
    },
    "years": {
        "1858": [
            "Year of publication of 'Four years in the government exploring expedition commanded by captain Charles Wilkes to the Island of Madeira, Cape Verdes, Brazil...'"
        ]
    }
}