{
    "id": 2641,
    "lang": "ru",
    "is_original": false,
    "title": "Солома",
    "fl": "С",
    "original_title": "Palha-Carga",
    "body": "Народное название Festuca Donax, злак высотой от 50 до 150 см с широкими листьями и колосками, собранными в широкие, рыхлые и иногда изогнутые метелки. Это растение часто встречается в ущельях внутренних районов Мадейры. Brachypodium silvaticum с крупными колосками, собранными в слегка наклоненный колос, также известен под названием солома в разных частях острова.",
    "categories": [
        "biology"
    ],
    "freguesias": [],
    "locations": {},
    "people": {},
    "years": {}
}