{
    "id": 2674,
    "lang": "ru",
    "is_original": false,
    "title": "Пассуш ди Фрейташ (д-р Мануэл)",
    "fl": "П",
    "original_title": "Passos de Freitas (Dr. Manuel)",
    "body": "Родился в Кальете 3 марта 1872 года, окончил юридический факультет Коимбрского университета в 1896 году. Он почетный секретарь Генерального совета округа и очень известный музыкант, дирижер музыкальной группы его имени и дирижер мадейрского хора, который несколько раз имел возможность оценить публика театра доктора Мануэла де Арриаги в Фуншале.",
    "categories": [
        "history",
        "culture"
    ],
    "freguesias": [],
    "locations": {
        "Кальета": [
            "Место рождения"
        ],
        "Коимбрский университет": [
            "Место учебы"
        ],
        "Фуншал": [
            "Место выступлений"
        ]
    },
    "people": {},
    "years": {
        "1872": [
            "Год рождения"
        ],
        "1896": [
            "Год окончания"
        ]
    }
}