{
    "id": 2739,
    "lang": "ru",
    "is_original": false,
    "title": "Перейра (Дуарти Содри)",
    "fl": "П",
    "original_title": "Pereira (Duarte Sodré)",
    "body": "15 ноября 1703 года он был назначен губернатором и генерал-капитаном Мадейры и вступил в должность 20 апреля 1704 года.",
    "categories": [
        "history"
    ],
    "freguesias": [],
    "locations": {},
    "people": {
        "Дуарти Содри Перейра": [
            "Назначение губернатором и генерал-капитаном Мадейры"
        ]
    },
    "years": {
        "1703": [
            "Назначение губернатором и генерал-капитаном"
        ],
        "1704": [
            "Вступление в должность"
        ]
    }
}