{
    "id": 3014,
    "lang": "ru",
    "is_original": false,
    "title": "Королевская площадь",
    "fl": "К",
    "original_title": "Real (Praça)",
    "body": "Так называлась во время правления Мигела I площадь Конституции, которая сейчас является частью проспекта доктора Мануэла ди Арриаги. На Королевской площади проходили парады войск и торжества во времена узурпации.",
    "categories": [
        "history"
    ],
    "freguesias": [],
    "locations": {
        "Проспект доктора Мануэла ди Арриаги": [
            "Бывшая площадь Конституции, названная Королевской во время правления Мигела I"
        ]
    },
    "people": {},
    "years": {}
}