{
    "id": 3015,
    "lang": "ru",
    "is_original": false,
    "title": "Реалист (Priacanthus fulgens)",
    "fl": "Р",
    "original_title": "Realista (Priacanthus fulgens)",
    "body": "Рыба семейства прикантовых, которая иногда ловится у берегов Мадейры. Легко отличается от любого другого вида красивым красным цветом, преобладающим на ее теле. Обычно попадается в прибрежные сети.",
    "categories": [
        "biology"
    ],
    "freguesias": [],
    "locations": {},
    "people": {},
    "years": {}
}