{
    "id": 3286,
    "lang": "ru",
    "is_original": false,
    "title": "Прощание с зимой (Chrysanthemum indicum)",
    "fl": "П",
    "original_title": "Saudades de Inverno (Chrysanthemum indicum)",
    "body": "Широко культивируемый цветок в садах Мадейры. Производит многочисленные и крупные соцветия, довольно изменчивые как по размеру, так и по цвету цветков. Это растение также называют прощанием с летом.",
    "categories": [
        "biology",
        "culture"
    ],
    "freguesias": [],
    "locations": {
        "Сады Мадейры": [
            "Место, где культивируется цветок Прощание с зимой"
        ]
    },
    "people": {},
    "years": {}
}