{
    "id": 3555,
    "lang": "ru",
    "is_original": false,
    "title": "Увейра (Vaccinium maderense)",
    "fl": "У",
    "original_title": "Uveira (Vaccinium maderense)",
    "body": "Кустарник или небольшое дерево, часто встречающееся в горах Мадейры, где оно образует иногда довольно обширные заросли. Листья ланцетовидные, часто красноватые, венчики шаровидно-колокольчатые, с красными пятнами. Древесина, которая довольно прочная, используется как топливо и для производства древесного угля, а из ягод делают варенье, полезное при лечении кашля и простуд.",
    "categories": [
        "biology"
    ],
    "freguesias": [],
    "locations": {},
    "people": {},
    "years": {}
}