{
    "id": 1769,
    "lang": "uk",
    "is_original": false,
    "title": "Непорочне Серце Марії (Каплиця)",
    "fl": "Н",
    "original_title": "Imaculado Coração de Maria (Capela do)",
    "body": "У 1918 році розпочалося будівництво каплиці цього присвячення на місці Фаха-ду-Пенеду парафії Боавентура з ініціативи та наполегливих зусиль пані Марії Маргариди душ Анжуш Рібейру, яка проживає в тому ж місці. 23 серпня 1919 року її урочисто освятив єпископ дієцезії антоніо мануель перейра рібейру.",
    "categories": [
        "religion"
    ],
    "freguesias": [
        "Boaventura"
    ],
    "locations": {
        "Фаха-ду-Пенеду": [
            "Місце"
        ],
        "Боавентура": [
            "Парафія"
        ]
    },
    "people": {
        "Пані Марія Маргарида душ Анжуш Рібейру": [
            "Ініціатор будівництва"
        ],
        "Єпископ антоніо мануель перейра рібейру": [
            "Єпископ дієцезії"
        ]
    },
    "years": {
        "1918": [
            "Початок будівництва каплиці"
        ],
        "1919": [
            "Урочисте освячення каплиці"
        ]
    }
}