{
    "id": 2201,
    "lang": "uk",
    "is_original": false,
    "title": "Мармулано (Sideroxylon marmulano)",
    "fl": "М",
    "original_title": "Marmulano (Sideroxylon Marmulano)",
    "body": "Чагарник з родини сапотових, з молочним соком, обернено-яйцеподібними або обернено-яйцеподібно-довгастими, шкірястими, великими листками та дуже дрібними квітками, розташованими пучками в пазухах листків. Зустрічається в Порту-Моніш, Рібейра-да-Жанела, Сейшалі, Порту-Санту тощо. Дає жовтувату деревину, а його листя є гарним кормом.",
    "categories": [
        "biology"
    ],
    "freguesias": [
        "Ribeira da Janela",
        "Seixal"
    ],
    "locations": {
        "Порту-Моніш": [
            "Місцевість, де знаходиться чагарник мармулано"
        ]
    },
    "people": {},
    "years": {}
}