{
    "id": 23,
    "lang": "uk",
    "is_original": false,
    "title": "Акація",
    "fl": "А",
    "original_title": "Acácia",
    "body": "Цей рід родини бобових, підродини мімозових, представлений на Мадейрі багатьма видами, одні зі складним листям, інші з листям, зведеним до філодіїв (черешків у формі листя). До першої групи належать: Acacia dealbata (біла акація), дуже поширена в Монте, Шупані тощо; A. Farnesiana (жовтий аромат), культивується в садах і напівдикоросла в різних прибережних районах; A Leucocephala (білий аромат), напівдикий чагарник у Ґорґулью та Прая-Формозі; і A (Albizzia) tophantha, майже завжди чагарниковий вид, що акліматизувався, головним чином, у Монте. До другої групи належать: A. Melanoxylon, культивується на фермах, площах та деяких вулицях; і A. retinoides, A. Sophorae та A. longifolia, поширені на фермах та в садах Мадейри. Акації родом з Австралії та теплих регіонів Америки, Азії та Африки, на острові можна знайти багато інших видів, крім тих, які ми згадали. Робінія псевдоакація, помилково відома на Мадейрі як акація, - колючий деревний вид, що належить до підродини метеликових і родом з Північної Америки, який легко розпізнати за своїм непарноперистим листям і білими ароматними квітами, зібраними в суцвіття.",
    "categories": [
        "biology"
    ],
    "freguesias": [],
    "locations": {},
    "people": {},
    "years": {}
}