{
    "id": 2786,
    "lang": "uk",
    "is_original": false,
    "title": "П'єдаде",
    "fl": "П",
    "original_title": "Piedade",
    "body": "Населений пункт парафії Жардін-ду-Мар, де знаходиться каплиця Носса-Сеньйора-да-П'єдаде з прилеглим маєтком, що належить вінкулованому будинку Коутуш Кардозуш. Була заснована у 1730 році моргаду Жуаном ду Коуту Кардозу і перебудована його наступником Франсішку Жуаном ді Вашконселуш ді Коуту Кардозу у 1825 році.",
    "categories": [
        "religion"
    ],
    "freguesias": [
        "Jardim do Mar"
    ],
    "locations": {},
    "people": {
        "Жуан ду Коуту Кардозу": [
            "Засновник каплиці"
        ],
        "Франсішку Жуан ді Вашконселуш ді Коуту Кардозу": [
            "Перебудовник каплиці"
        ]
    },
    "years": {
        "1730": [
            "Заснування каплиці"
        ],
        "1825": [
            "Перебудова каплиці"
        ]
    }
}