{
    "id": 543,
    "lang": "uk",
    "is_original": false,
    "title": "Огірок звичайний (Borago officinalis)",
    "fl": "О",
    "original_title": "Borragem (Borago officinalis)",
    "body": "Емолієнтна, потогінна та сечогінна рослина, культивується та натуралізована в Сан-Мартіню, Сан-Роке, Канісу тощо. Цей представник родини шорстколистих, родом з Європи, впізнається за своїми великими синіми або білими квітами, що згодом звисають, та жорстким опушеним листям з грубими волосками.",
    "categories": [
        "biology"
    ],
    "freguesias": [
        "S. Martinho",
        "S. Roque",
        "Caniço"
    ],
    "locations": {},
    "people": {},
    "years": {}
}