{
    "id": 2601,
    "lang": "ua",
    "is_original": false,
    "title": "Орнелаш де Вашконселуш (Айреш де)",
    "fl": "О",
    "original_title": "Ornelas de Vasconcelos (Ayres de)",
    "body": "У зв’язку з народним заколотом, який скинув і ув’язнив губернатора Франсішку де Машкареньяша (див. це ім’я), «18 вересня 1668 року Айреш де Орнеллаш був обраний дворянством і народом губернатором і генерал-капітаном. На цій високій посаді його затвердив принц-регент Педру, і він залишався на ній до вступу на посаду свого наступника Айреша де Салданьї наступного 1669 року.\n\nВін був сьомим прадідом видатних мадейрців архієпископа Д. Айреша де Орнелаша та пера королівства Агоштінью де Орнелаша.»",
    "categories": [
        "history"
    ],
    "freguesias": [],
    "locations": {},
    "people": {
        "Франсішку де Машкареньяш": [
            "Губернатор"
        ],
        "Педру": [
            "Принц-регент"
        ],
        "Айреш де Салданья": [
            "Наступник"
        ],
        "Д. Айреш де Орнелаш": [
            "Архієпископ"
        ],
        "Агоштінью де Орнелаш": [
            "Пер королівства"
        ]
    },
    "years": {
        "1668": [
            "Обрання Айреша де Орнеллаша дворянством і народом губернатором і генерал-капітаном"
        ],
        "1669": [
            "Вступ на посаду його наступника Айреша де Салданьї"
        ]
    }
}