{
    "id": 3675,
    "lang": "ua",
    "is_original": false,
    "title": "Вотсон (Роберто Буг)",
    "fl": "В",
    "original_title": "Watson (Roberto Boog)",
    "body": "Доктор права та конхіолог з Англії, який у 1864-1874 роках вивчав морські молюски Мадейри, одночасно виконуючи обов'язки капелана однієї з протестантських церков Фуншала. Він вже помер (1921). Він написав роботу під назвою \"Про морських молюсків Мадейри\" (Журнал Ліннеївського товариства, XXVI, 1897), займався тією ж темою в 1873 році в Мемуарах Зоологічного товариства Лондона. У своїй роботі, опублікованій у 1897 році, Вотсон згадує 382 види морських молюсків, описуючи 35, які, на його думку, були новими. Як і його співвітчизник Волластон, Вотсон іноді намагався применшити в своїх роботах інших натуралістів, що не властиво вченому, а тим більше священику, хоча й протестанту. Мушлі Вотсона сьогодні належать англійському малакологу Томліну, як сказано в листі, надісланому в це місто (1921).",
    "categories": [
        "science"
    ],
    "freguesias": [],
    "locations": {},
    "people": {
        "Роберто Буг Вотсон": [
            "Доктор права та конхіолог з Англії"
        ]
    },
    "years": {
        "1864": [
            "Вивчав морські молюски Мадейри"
        ],
        "1874": [
            "Вивчав морські молюски Мадейри"
        ],
        "1921": [
            "Помер"
        ]
    }
}